iqvia_e360/__init__.py
iqvia_e360/e360_context.py
iqvia_e360/exceptions.py
iqvia_e360/models.py
iqvia_e360/settings.py
iqvia_e360-0.9.6.dist-info/LICENSE.txt
iqvia_e360-0.9.6.dist-info/METADATA
iqvia_e360-0.9.6.dist-info/WHEEL
iqvia_e360-0.9.6.dist-info/top_level.txt
iqvia_e360-0.9.6.dist-info/RECORD
