Metadata-Version: 2.1
Name: iqvia-e360
Version: 0.9.6
Summary: E360 Clients Wrapper for Python
Author: IQVIA
Author-email: e360pypi@iqvia.com
License: Apache License 2.0
Classifier: Environment :: Web Environment
Classifier: Intended Audience :: Developers
Classifier: License :: OSI Approved :: Apache Software License
Classifier: Operating System :: OS Independent
Classifier: Programming Language :: Python
Classifier: Programming Language :: Python :: 3.8
Classifier: Programming Language :: Python :: 3.9
Classifier: Programming Language :: Python :: 3.10
Classifier: Programming Language :: Python :: 3.11
Classifier: Topic :: Internet :: WWW/HTTP
Classifier: Topic :: Internet :: WWW/HTTP :: Dynamic Content
Requires-Python: >=3.8
License-File: LICENSE.txt
Requires-Dist: adt-clients (<3,>=2.0.0)
Requires-Dist: analytic-workbench-clients
Requires-Dist: clients-core (<3,>=2.1.3)
Requires-Dist: e360-charting (<2,>=1.3.0)
Requires-Dist: dashboard-clients (<4,>=3.0.1)
Requires-Dist: plotly
Requires-Dist: pandas
Requires-Dist: file-service-client (<3,>=2.0.1)
Requires-Dist: pydantic
Requires-Dist: sd-clients (<3,>=2.2.0)
Requires-Dist: vrs-clients (<3,>=2.0.0)
Requires-Dist: workspace-clients (<3,>=2.1.1)
